pycync/__init__.py
pycync/auth.py
pycync/const.py
pycync/cync.py
pycync/exceptions.py
pycync/user.py
pycync/devices/__init__.py
pycync/devices/capabilities.py
pycync/devices/controllable.py
pycync/devices/device_storage.py
pycync/devices/device_types.py
pycync/devices/devices.py
pycync/devices/groups.py
pycync/tcp/command_client.py
pycync/tcp/inner_packet_builder.py
pycync/tcp/packet.py
pycync/tcp/packet_builder.py
pycync/tcp/packet_parser.py
pycync/tcp/tcp_manager.py
pycync-0.4.2.dist-info/METADATA
pycync-0.4.2.dist-info/WHEEL
pycync-0.4.2.dist-info/licenses/LICENSE
pycync-0.4.2.dist-info/RECORD
