Metadata-Version: 2.4
Name: pycync
Version: 0.4.2
Summary: A Python library to communicate with Cync devices.
Project-URL: Homepage, https://github.com/Kinachi249/pycync
Project-URL: Issues, https://github.com/Kinachi249/pycync/issues
Author: @Kinachi249
License: GPL-3.0-or-later
License-File: LICENSE
Keywords: cync,ge,lighting,smart home
Classifier: Environment :: Other Environment
Classifier: Intended Audience :: Developers
Classifier: License :: OSI Approved :: GNU General Public License v3 or later (GPLv3+)
Classifier: Operating System :: OS Independent
Classifier: Programming Language :: Python :: 3
Classifier: Programming Language :: Python :: 3.9
Classifier: Programming Language :: Python :: 3.10
Classifier: Programming Language :: Python :: 3.11
Classifier: Programming Language :: Python :: 3.12
Classifier: Topic :: Home Automation
Classifier: Topic :: Software Development :: Libraries :: Python Modules
Requires-Python: >=3.9.0
Requires-Dist: aiohttp>=3
